lazylights.py
setup.py
lazylights.egg-info/PKG-INFO
lazylights.egg-info/SOURCES.txt
lazylights.egg-info/dependency_links.txt
lazylights.egg-info/top_level.txt