Metadata-Version: 1.0
Name: lazylights
Version: 2.0.0rc1
Summary: Python tools for controlling Lifx bulbs.
Home-page: http://github.com/mpapi/lazylights/
Author: Matt Papi
Author-email: mmpapi@gmail.com
License: LICENSE
Platform: UNKNOWN
